lab4/full_adder.v
module full_adder(x, y, cin, sum, cout);

input x, y, cin;
output sum, cout;

assign sum=cin^x^y;
assign cout=(x&y)|(x&cin)|(cin&y);

endmodule

lab4/full_adder_tb.v
`timescale 1ns/1ns
`include "full_adder.v"

module full_adder_tb();
reg x,y, cin;
wire sum, cout;

full_adder full_adder_instance(x, y, cin, sum, cout);
initial
begin

$dumpfile("full_adder_tb.vcd");
$dumpvars(0, full_adder_tb);

cin=1'b0;x =1'b0;y=1'b0;
#10;
cin=1'b0;x =1'b0;y=1'b1;
#10;
cin=1'b0;x =1'b1;y=1'b0;
#10;
cin=1'b0;x =1'b1;y=1'b1;
#10;
cin=1'b1;x =1'b0;y=1'b0;
#10;
cin=1'b1;x =1'b0;y=1'b1;
#10;
cin=1'b1;x =1'b1;y=1'b0;
#10;
cin=1'b1;x =1'b1;y=1'b1;
#10;

$display("Test complete");
end
endmodule

lab4/full_adder_tb.vcd
$date
	Mon Aug 18 14:17:05 2025
$end
$version
	Icarus Verilog
$end
$timescale
	1ns
$end
$scope module full_adder_tb $end
$var wire 1 ! sum $end
$var wire 1 " cout $end
$var reg 1 # cin $end
$var reg 1 $ x $end
$var reg 1 % y $end
$scope module full_adder_instance $end
$var wire 1 # cin $end
$var wire 1 " cout $end
$var wire 1 ! sum $end
$var wire 1 $ x $end
$var wire 1 % y $end
$upscope $end
$upscope $end
$enddefinitions $end
#0
$dumpvars
0%
0$
0#
0"
0!
$end
#10
1!
1%
#20
0%
1$
#30
1"
0!
1%
#40
0"
1!
0%
0$
1#
#50
1"
0!
1%
#60
0%
1$
#70
1!
1%
