lab6/dec_2to4_to_dec4to16.v
module dec_2to4(w, y, en);
input [1:0] w; 
input en; 
output reg [3:0] y; 

always@(w or en)
case({en,w})
4:y =4'b1110;
5:y =4'b1101;
6:y =4'b1011;
7:y =4'b0111;
default:y=15;
endcase

endmodule

module dec_4to16(w, y, en);
input[3:0] w; 
input en; 
output[15:0] y; 
wire [3:0]inter;
dec_2to4 dec0(w[3:2], inter, en);
dec_2to4 dec1(w[1:0], y[3:0], ~inter[0]);
dec_2to4 dec2(w[1:0], y[7:4], ~inter[1]);
dec_2to4 dec3(w[1:0], y[11:8], ~inter[2]);
dec_2to4 dec4(w[1:0], y[15:12], ~inter[3]);

endmodule

lab6/dec_2to4_to_dec4to16_tb.v
`timescale 1ns/1ns
`include "dec_2to4_to_dec4to16.v"

module dec_2to4_to_dec4to16_tb();
reg[3:0] w; 
reg en; 
wire[15:0] y; 

dec_4to16 dec(w, y, en);
initial
begin
$dumpfile("dec_2to4_to_dec4to16_tb.vcd");
$dumpvars(0, dec_2to4_to_dec4to16_tb);

w=15; en= 1; 
#10;
w=11; en= 1; 
#10;
w=10; en= 1; 
#10;
w=9; en= 1; 
#10;
w=8; en= 1; 
#10;
w=4; en= 1; 
#10;
w=3; en= 1; 
#10;
w=1; en= 1; 
#10;

end
endmodule

lab6/dec_2to4_to_dec4to16_tb.vcd
$date
	Mon Sep 22 15:28:31 2025
$end
$version
	Icarus Verilog
$end
$timescale
	1ns
$end
$scope module dec_2to4_to_dec4to16_tb $end
$var wire 16 ! y [15:0] $end
$var reg 1 " en $end
$var reg 4 # w [3:0] $end
$scope module dec $end
$var wire 1 " en $end
$var wire 4 $ w [3:0] $end
$var wire 16 % y [15:0] $end
$var wire 4 & inter [3:0] $end
$scope module dec0 $end
$var wire 1 " en $end
$var wire 2 ' w [1:0] $end
$var reg 4 ( y [3:0] $end
$upscope $end
$scope module dec1 $end
$var wire 1 ) en $end
$var wire 2 * w [1:0] $end
$var reg 4 + y [3:0] $end
$upscope $end
$scope module dec2 $end
$var wire 1 , en $end
$var wire 2 - w [1:0] $end
$var reg 4 . y [3:0] $end
$upscope $end
$scope module dec3 $end
$var wire 1 / en $end
$var wire 2 0 w [1:0] $end
$var reg 4 1 y [3:0] $end
$upscope $end
$scope module dec4 $end
$var wire 1 2 en $end
$var wire 2 3 w [1:0] $end
$var reg 4 4 y [3:0] $end
$upscope $end
$upscope $end
$upscope $end
$enddefinitions $end
#0
$dumpvars
b111 4
b11 3
12
b1111 1
b11 0
0/
b1111 .
b11 -
0,
b1111 +
b11 *
0)
b111 (
b11 '
b111 &
b111111111111111 %
b1111 $
b1111 #
1"
b111111111111111 !
$end
#10
b1111 4
b1111011111111111 !
b1111011111111111 %
b111 1
02
1/
b1011 &
b1011 (
b10 '
b1011 #
b1011 $
#20
b1111101111111111 !
b1111101111111111 %
b1011 1
b10 *
b10 -
b10 0
b10 3
b1010 #
b1010 $
#30
b1111110111111111 !
b1111110111111111 %
b1101 1
b1 *
b1 -
b1 0
b1 3
b1001 #
b1001 $
#40
b1111111011111111 !
b1111111011111111 %
b1110 1
b0 *
b0 -
b0 0
b0 3
b1000 #
b1000 $
#50
b1111 1
b1111111111101111 !
b1111111111101111 %
b1110 .
0/
1,
b1101 &
b1101 (
b1 '
b100 #
b100 $
#60
b111 +
0,
1)
b1110 &
b1110 (
b1111111111110111 !
b1111111111110111 %
b1111 .
b0 '
b11 *
b11 -
b11 0
b11 3
b11 #
b11 $
#70
b1111111111111101 !
b1111111111111101 %
b1101 +
b1 *
b1 -
b1 0
b1 3
b1 #
b1 $
