lab6/priority_enc_16to4.v
module priority_enc_16to4(w, y, z);
input[15:0] w; 
output reg[3:0] y;
output reg z; 
integer k; 

always@(w)
begin
y=4'bxxxx; 
z =0; 
for(k= 0; k<15; k= k+1)
if(w[k])
begin
y = k;
z = 1;
end
end
endmodule

lab6/priority_enc_16to4_tb.v
`timescale 1ns/1ns
`include "priority_enc_16to4.v" 

module priority_enc_16to4_tb();
reg[15:0] w; 
wire[3:0] y;
wire z;

priority_enc_16to4 pri(w, y, z);
initial
begin

$dumpfile("priority_enc_16to4_tb.vcd");
$dumpvars(0,priority_enc_16to4_tb);

w =15;
#10;
w =16;
#10;
w =20;
#10;
w =4;
#10;
w =5;
#10;
w =7;
#10;
w =2;
#10;
w =3;
#10;
w =10;
#10;
w =1;
#10;
w =0;
#10;

end
endmodule

lab6/priority_enc_16to4_tb.vcd
$date
	Mon Sep 22 16:05:09 2025
$end
$version
	Icarus Verilog
$end
$timescale
	1ns
$end
$scope module priority_enc_16to4_tb $end
$var wire 1 ! z $end
$var wire 4 " y [3:0] $end
$var reg 16 # w [15:0] $end
$scope module pri $end
$var wire 16 $ w [15:0] $end
$var reg 4 % y [3:0] $end
$var reg 1 ! z $end
$var integer 32 & k [31:0] $end
$upscope $end
$upscope $end
$enddefinitions $end
#0
$dumpvars
b1111 &
b11 %
b1111 $
b1111 #
b11 "
1!
$end
#10
b1111 &
1!
b100 "
b100 %
b10000 #
b10000 $
#20
b1111 &
1!
b100 "
b100 %
b10100 #
b10100 $
#30
b1111 &
1!
b10 "
b10 %
b100 #
b100 $
#40
b1111 &
1!
b10 "
b10 %
b101 #
b101 $
#50
b1111 &
1!
b10 "
b10 %
b111 #
b111 $
#60
b1111 &
1!
b1 "
b1 %
b10 #
b10 $
#70
b1111 &
1!
b1 "
b1 %
b11 #
b11 $
#80
b1111 &
1!
b11 "
b11 %
b1010 #
b1010 $
#90
b1111 &
1!
b0 "
b0 %
b1 #
b1 $
#100
b1111 &
0!
bx "
bx %
b0 #
b0 $
