lab6/priority_enc_2to4.v
module priority_enc_2to4(w, y, z);
input [3:0] w; 
output reg[1:0] y; 
output reg z; 

always@(w)
begin 
z = 1; 
casex(w)
4'b1xxx:y =3;
4'b01xx:y =2;
4'b001x:y =1;
4'b0001:y =0;
default:
begin
z=0;
y=2'bxx;
end
endcase 
end
endmodule

lab6/priority_enc_2to4_tb.v
`timescale 1ns/1ns
`include "priority_enc_2to4.v" 

module priority_enc_2to4_tb();
reg [3:0] w; 
wire [1:0] y; 
wire z; 

priority_enc_2to4 priority(w, y, z);
initial
begin

$dumpfile("priority_enc_2to4_tb.vcd");
$dumpvars(0,priority_enc_2to4_tb);

w =8;
#10;
w =9;
#10;
w =10;
#10;
w =4;
#10;
w =5;
#10;
w =7;
#10;
w =2;
#10;
w =3;
#10;
w =10;
#10;
w =1;
#10;
w =0;
#10;

end
endmodule

lab6/priority_enc_2to4_tb.vcd
$date
	Mon Sep 22 15:55:23 2025
$end
$version
	Icarus Verilog
$end
$timescale
	1ns
$end
$scope module priority_enc_2to4_tb $end
$var wire 1 ! z $end
$var wire 2 " y [1:0] $end
$var reg 4 # w [3:0] $end
$scope module priority $end
$var wire 4 $ w [3:0] $end
$var reg 2 % y [1:0] $end
$var reg 1 ! z $end
$upscope $end
$upscope $end
$enddefinitions $end
#0
$dumpvars
b11 %
b1000 $
b1000 #
b11 "
1!
$end
#10
b1001 #
b1001 $
#20
b1010 #
b1010 $
#30
b10 "
b10 %
b100 #
b100 $
#40
b101 #
b101 $
#50
b111 #
b111 $
#60
b1 "
b1 %
b10 #
b10 $
#70
b11 #
b11 $
#80
b11 "
b11 %
b1010 #
b1010 $
#90
b0 "
b0 %
b1 #
b1 $
#100
bx "
bx %
0!
b0 #
b0 $
